collectmiddleware/__init__.py
collectmiddleware/__version__.py
collectmiddleware/middleware.py
collectmiddleware-0.1.0.dist-info/METADATA
collectmiddleware-0.1.0.dist-info/WHEEL
collectmiddleware-0.1.0.dist-info/RECORD
