Metadata-Version: 2.1
Name: collectmiddleware
Version: 0.1.0
Summary: this project consists of creating a middleware to transmit the data collected on an Object Request to a MongoDB Database for later analysis
License: MIT
Author: Darix SAMANI SIEWE
Author-email: samanidarix@gmail.com
Requires-Python: >=3.8,<4.0
Classifier: License :: OSI Approved :: MIT License
Classifier: Programming Language :: Python :: 3
Classifier: Programming Language :: Python :: 3.8
Classifier: Programming Language :: Python :: 3.9
Classifier: Programming Language :: Python :: 3.10
Classifier: Programming Language :: Python :: 3.11
Classifier: Programming Language :: Python :: 3.12
Requires-Dist: pymongo (>=4.7.3,<5.0.0)
Requires-Dist: starlette (>=0.37.2,<0.38.0)
Requires-Dist: typing-extensions (>=4.12.2,<5.0.0)
